README.md
setup.py
monorulerf/__init__.py
monorulerf/monorulerf.py
monorulerf/version.py
monorulerf.egg-info/PKG-INFO
monorulerf.egg-info/SOURCES.txt
monorulerf.egg-info/dependency_links.txt
monorulerf.egg-info/not-zip-safe
monorulerf.egg-info/requires.txt
monorulerf.egg-info/top_level.txt
monorulerf/data/boston.csv
monorulerf/tests/__init__.py
monorulerf/tests/test_monorulerf.py