Metadata-Version: 1.1
Name: monorulerf
Version: 0.4
Summary: 
